{
  "timestamp": "2025-12-15T21:40:51.562806",
  "ticker": "NVDA",
  "data_points": 2559,
  "latest_signal": {
    "date": "2025-12-15",
    "signal": "BUY",
    "position": "LONG",
    "phase_quadrant": "Quadrante 1 (Minimo -> Salita)",
    "phase_value": -2.85249674739204,
    "oscillator_value": -5.723249999999979,
    "signal_strength": 6.428013755431656,
    "confidence": "LOW",
    "price": 176.29,
    "timestamp": "2025-12-15T21:40:49.574968"
  },
  "backtest_metrics": {
    "total_return_%": 232.6860974922227,
    "max_drawdown_%": 0.22851573977646145,
    "sharpe_ratio": 0.8329016459916133,
    "sortino_ratio": Infinity,
    "calmar_ratio": 224.61504383985817,
    "total_trades": 9,
    "win_rate_%": 88.88888888888889,
    "profit_factor": 421.67707759709657
  },
  "cycle_analysis": {
    "dominant_period": 252.0,
    "p_value": 0.0,
    "significant": "True"
  }
}